moumoutest/test1.py
moumoutest/test2.py
moumoutest-0.0.0.1.dist-info/METADATA
moumoutest-0.0.0.1.dist-info/WHEEL
moumoutest-0.0.0.1.dist-info/top_level.txt
moumoutest-0.0.0.1.dist-info/RECORD
