Metadata-Version: 2.1
Name: moumoutest
Version: 0.0.0.1
Summary: My First Test Package
Home-page: https://blog.naver.com/lovemhy26
Author: Hayoung Mo
Author-email: lovemhy26@gmail.com
License: MIT
Requires-Python: >=3
